{
  "stats": {
    "submitted": 75,
    "finished": 75,
    "running": 0
  },
  "data": [
    {
      "config_id": 1,
      "instance": null,
      "seed": 196930371,
      "budget": null,
      "cost": 21.2680398154463,
      "time": 0.0,
      "cpu_time": 0.0,
      "status": 1,
      "starttime": 1781223306.6566746,
      "endtime": 1781223306.657674,
      "additional_info": {}
    },
    {
      "config_id": 2,
      "instance": null,
      "seed": 196930371,
      "budget": null,
      "cost": 53.10196727238126,
      "time": 0.0,
      "cpu_time": 0.0,
      "status": 1,
      "starttime": 1781223306.6659534,
      "endtime": 1781223306.6669655,
      "additional_info": {}
    },
    {
      "config_id": 3,
      "instance": null,
      "seed": 196930371,
      "budget": null,
      "cost": 19.406472443520137,
      "time": 0.0,
      "cpu_time": 0.0,
      "status": 1,
      "starttime": 1781223306.6736052,
      "endtime": 1781223306.6752803,
      "additional_info": {}
    },
    {
      "config_id": 4,
      "instance": null,
      "seed": 196930371,
      "budget": null,
      "cost": 6.363361671279159,
      "time": 0.0,
      "cpu_time": 0.0,
      "status": 1,
      "starttime": 1781223306.6863356,
      "endtime": 1781223306.6872685,
      "additional_info": {}
    },
    {
      "config_id": 5,
      "instance": null,
      "seed": 196930371,
      "budget": null,
      "cost": 88.32944697940886,
      "time": 0.0,
      "cpu_time": 0.0,
      "status": 1,
      "starttime": 1781223306.6954734,
      "endtime": 1781223306.6976178,
      "additional_info": {}
    },
    {
      "config_id": 6,
      "instance": null,
      "seed": 196930371,
      "budget": null,
      "cost": 122.63316556676793,
      "time": 0.0,
      "cpu_time": 0.0,
      "status": 1,
      "starttime": 1781223306.7024736,
      "endtime": 1781223306.7035778,
      "additional_info": {}
    },
    {
      "config_id": 7,
      "instance": null,
      "seed": 196930371,
      "budget": null,
      "cost": 15.546406945373768,
      "time": 0.0,
      "cpu_time": 0.0,
      "status": 1,
      "starttime": 1781223306.711707,
      "endtime": 1781223306.7148578,
      "additional_info": {}
    },
    {
      "config_id": 8,
      "instance": null,
      "seed": 196930371,
      "budget": null,
      "cost": 69.54037338170716,
      "time": 0.0,
      "cpu_time": 0.0,
      "status": 1,
      "starttime": 1781223306.7216144,
      "endtime": 1781223306.7226179,
      "additional_info": {}
    },
    {
      "config_id": 9,
      "instance": null,
      "seed": 196930371,
      "budget": null,
      "cost": 24.370586710673965,
      "time": 0.0,
      "cpu_time": 0.0,
      "status": 1,
      "starttime": 1781223306.728842,
      "endtime": 1781223306.731169,
      "additional_info": {}
    },
    {
      "config_id": 10,
      "instance": null,
      "seed": 196930371,
      "budget": null,
      "cost": 86.89717173914661,
      "time": 0.0,
      "cpu_time": 0.0,
      "status": 1,
      "starttime": 1781223306.7362523,
      "endtime": 1781223306.7372644,
      "additional_info": {}
    },
    {
      "config_id": 11,
      "instance": null,
      "seed": 196930371,
      "budget": null,
      "cost": 7.196261911846501,
      "time": 0.0,
      "cpu_time": 0.0,
      "status": 1,
      "starttime": 1781223306.7424467,
      "endtime": 1781223306.7435532,
      "additional_info": {}
    },
    {
      "config_id": 12,
      "instance": null,
      "seed": 196930371,
      "budget": null,
      "cost": 64.6705049086317,
      "time": 0.0,
      "cpu_time": 0.0,
      "status": 1,
      "starttime": 1781223306.7504592,
      "endtime": 1781223306.7525623,
      "additional_info": {}
    },
    {
      "config_id": 13,
      "instance": null,
      "seed": 196930371,
      "budget": null,
      "cost": 12.051840473554039,
      "time": 0.0,
      "cpu_time": 0.0,
      "status": 1,
      "starttime": 1781223306.7580016,
      "endtime": 1781223306.7590184,
      "additional_info": {}
    },
    {
      "config_id": 14,
      "instance": null,
      "seed": 196930371,
      "budget": null,
      "cost": 79.68388810655185,
      "time": 0.0,
      "cpu_time": 0.0,
      "status": 1,
      "starttime": 1781223306.765924,
      "endtime": 1781223306.7670255,
      "additional_info": {}
    },
    {
      "config_id": 15,
      "instance": null,
      "seed": 196930371,
      "budget": null,
      "cost": 19.756303513772817,
      "time": 0.0,
      "cpu_time": 0.0,
      "status": 1,
      "starttime": 1781223306.7730124,
      "endtime": 1781223306.774013,
      "additional_info": {}
    },
    {
      "config_id": 16,
      "instance": null,
      "seed": 196930371,
      "budget": null,
      "cost": 103.34926725882943,
      "time": 0.0,
      "cpu_time": 0.0,
      "status": 1,
      "starttime": 1781223306.7810051,
      "endtime": 1781223306.782022,
      "additional_info": {}
    },
    {
      "config_id": 17,
      "instance": null,
      "seed": 196930371,
      "budget": null,
      "cost": 29.047736570755774,
      "time": 0.0,
      "cpu_time": 0.0,
      "status": 1,
      "starttime": 1781223306.7889173,
      "endtime": 1781223306.7899187,
      "additional_info": {}
    },
    {
      "config_id": 18,
      "instance": null,
      "seed": 196930371,
      "budget": null,
      "cost": 190.0133307469994,
      "time": 0.0,
      "cpu_time": 0.0,
      "status": 1,
      "starttime": 1781223306.7969255,
      "endtime": 1781223306.7995021,
      "additional_info": {}
    },
    {
      "config_id": 19,
      "instance": null,
      "seed": 196930371,
      "budget": null,
      "cost": 6.6079645107667435,
      "time": 0.0,
      "cpu_time": 0.0,
      "status": 1,
      "starttime": 1781223310.8160038,
      "endtime": 1781223310.8180997,
      "additional_info": {}
    },
    {
      "config_id": 20,
      "instance": null,
      "seed": 196930371,
      "budget": null,
      "cost": 5.041732597846643,
      "time": 0.0,
      "cpu_time": 0.0,
      "status": 1,
      "starttime": 1781223310.831414,
      "endtime": 1781223310.833456,
      "additional_info": {}
    },
    {
      "config_id": 21,
      "instance": null,
      "seed": 196930371,
      "budget": null,
      "cost": 2.10895875941152,
      "time": 0.0,
      "cpu_time": 0.0,
      "status": 1,
      "starttime": 1781223310.8495085,
      "endtime": 1781223310.8515043,
      "additional_info": {}
    },
    {
      "config_id": 22,
      "instance": null,
      "seed": 196930371,
      "budget": null,
      "cost": 4.0512857969040645,
      "time": 0.0,
      "cpu_time": 0.0,
      "status": 1,
      "starttime": 1781223310.8696983,
      "endtime": 1781223310.8717961,
      "additional_info": {}
    },
    {
      "config_id": 23,
      "instance": null,
      "seed": 196930371,
      "budget": null,
      "cost": 16.28845646970928,
      "time": 0.0,
      "cpu_time": 0.0,
      "status": 1,
      "starttime": 1781223310.8833458,
      "endtime": 1781223310.8843367,
      "additional_info": {}
    },
    {
      "config_id": 24,
      "instance": null,
      "seed": 196930371,
      "budget": null,
      "cost": 2.284402994148108,
      "time": 0.0,
      "cpu_time": 0.0,
      "status": 1,
      "starttime": 1781223310.8923461,
      "endtime": 1781223310.8942406,
      "additional_info": {}
    },
    {
      "config_id": 25,
      "instance": null,
      "seed": 196930371,
      "budget": null,
      "cost": 4.252298842603365,
      "time": 0.0,
      "cpu_time": 0.0,
      "status": 1,
      "starttime": 1781223310.9033077,
      "endtime": 1781223310.9044073,
      "additional_info": {}
    },
    {
      "config_id": 26,
      "instance": null,
      "seed": 196930371,
      "budget": null,
      "cost": 2.3808369816673514,
      "time": 0.0,
      "cpu_time": 0.0,
      "status": 1,
      "starttime": 1781223310.9144256,
      "endtime": 1781223310.91553,
      "additional_info": {}
    },
    {
      "config_id": 27,
      "instance": null,
      "seed": 196930371,
      "budget": null,
      "cost": 3.469616249572619,
      "time": 0.0,
      "cpu_time": 0.0,
      "status": 1,
      "starttime": 1781223314.451789,
      "endtime": 1781223314.4547868,
      "additional_info": {}
    },
    {
      "config_id": 28,
      "instance": null,
      "seed": 196930371,
      "budget": null,
      "cost": 26.774686601746325,
      "time": 0.0009982585906982422,
      "cpu_time": 0.0,
      "status": 1,
      "starttime": 1781223314.468786,
      "endtime": 1781223314.470786,
      "additional_info": {}
    },
    {
      "config_id": 29,
      "instance": null,
      "seed": 196930371,
      "budget": null,
      "cost": 6.865093292960037,
      "time": 0.0,
      "cpu_time": 0.0,
      "status": 1,
      "starttime": 1781223314.481879,
      "endtime": 1781223314.4828815,
      "additional_info": {}
    },
    {
      "config_id": 30,
      "instance": null,
      "seed": 196930371,
      "budget": null,
      "cost": 26.601108900829786,
      "time": 0.0,
      "cpu_time": 0.0,
      "status": 1,
      "starttime": 1781223314.4952135,
      "endtime": 1781223314.4963055,
      "additional_info": {}
    },
    {
      "config_id": 31,
      "instance": null,
      "seed": 196930371,
      "budget": null,
      "cost": 16.59761449390247,
      "time": 0.0,
      "cpu_time": 0.0,
      "status": 1,
      "starttime": 1781223314.506767,
      "endtime": 1781223314.5076962,
      "additional_info": {}
    },
    {
      "config_id": 32,
      "instance": null,
      "seed": 196930371,
      "budget": null,
      "cost": 8.132697089855789,
      "time": 0.0,
      "cpu_time": 0.0,
      "status": 1,
      "starttime": 1781223314.5207644,
      "endtime": 1781223314.5217636,
      "additional_info": {}
    },
    {
      "config_id": 33,
      "instance": null,
      "seed": 196930371,
      "budget": null,
      "cost": 0.7059409717130372,
      "time": 0.0,
      "cpu_time": 0.0,
      "status": 1,
      "starttime": 1781223314.5331578,
      "endtime": 1781223314.5341575,
      "additional_info": {}
    },
    {
      "config_id": 34,
      "instance": null,
      "seed": 196930371,
      "budget": null,
      "cost": 0.5012265457416607,
      "time": 0.0,
      "cpu_time": 0.0,
      "status": 1,
      "starttime": 1781223314.544598,
      "endtime": 1781223314.5469778,
      "additional_info": {}
    },
    {
      "config_id": 35,
      "instance": null,
      "seed": 196930371,
      "budget": null,
      "cost": 11.997784251334828,
      "time": 0.0,
      "cpu_time": 0.0,
      "status": 1,
      "starttime": 1781223318.0798435,
      "endtime": 1781223318.0818613,
      "additional_info": {}
    },
    {
      "config_id": 36,
      "instance": null,
      "seed": 196930371,
      "budget": null,
      "cost": 4.058059951029637,
      "time": 0.0,
      "cpu_time": 0.0,
      "status": 1,
      "starttime": 1781223318.1005154,
      "endtime": 1781223318.1025045,
      "additional_info": {}
    },
    {
      "config_id": 37,
      "instance": null,
      "seed": 196930371,
      "budget": null,
      "cost": 84.46455027863576,
      "time": 0.0,
      "cpu_time": 0.0,
      "status": 1,
      "starttime": 1781223318.1185827,
      "endtime": 1781223318.1195822,
      "additional_info": {}
    },
    {
      "config_id": 38,
      "instance": null,
      "seed": 196930371,
      "budget": null,
      "cost": 131.46887803958248,
      "time": 0.0,
      "cpu_time": 0.0,
      "status": 1,
      "starttime": 1781223318.1334426,
      "endtime": 1781223318.1354442,
      "additional_info": {}
    },
    {
      "config_id": 39,
      "instance": null,
      "seed": 196930371,
      "budget": null,
      "cost": 244.20040839601802,
      "time": 0.0,
      "cpu_time": 0.0,
      "status": 1,
      "starttime": 1781223318.1497712,
      "endtime": 1781223318.1517696,
      "additional_info": {}
    },
    {
      "config_id": 40,
      "instance": null,
      "seed": 196930371,
      "budget": null,
      "cost": 0.6182213180142053,
      "time": 0.0,
      "cpu_time": 0.0,
      "status": 1,
      "starttime": 1781223318.1668348,
      "endtime": 1781223318.167828,
      "additional_info": {}
    },
    {
      "config_id": 41,
      "instance": null,
      "seed": 196930371,
      "budget": null,
      "cost": 102.43608087036364,
      "time": 0.0,
      "cpu_time": 0.0,
      "status": 1,
      "starttime": 1781223318.184544,
      "endtime": 1781223318.1865385,
      "additional_info": {}
    },
    {
      "config_id": 42,
      "instance": null,
      "seed": 196930371,
      "budget": null,
      "cost": 8.549513572926124,
      "time": 0.0,
      "cpu_time": 0.0,
      "status": 1,
      "starttime": 1781223318.2001321,
      "endtime": 1781223318.2012608,
      "additional_info": {}
    },
    {
      "config_id": 43,
      "instance": null,
      "seed": 196930371,
      "budget": null,
      "cost": 0.8508783289512127,
      "time": 0.0,
      "cpu_time": 0.0,
      "status": 1,
      "starttime": 1781223322.7714415,
      "endtime": 1781223322.773441,
      "additional_info": {}
    },
    {
      "config_id": 44,
      "instance": null,
      "seed": 196930371,
      "budget": null,
      "cost": 0.8499424891878196,
      "time": 0.0,
      "cpu_time": 0.0,
      "status": 1,
      "starttime": 1781223322.7924407,
      "endtime": 1781223322.7944336,
      "additional_info": {}
    },
    {
      "config_id": 45,
      "instance": null,
      "seed": 196930371,
      "budget": null,
      "cost": 0.9495383766068173,
      "time": 0.0,
      "cpu_time": 0.0,
      "status": 1,
      "starttime": 1781223322.815912,
      "endtime": 1781223322.817906,
      "additional_info": {}
    },
    {
      "config_id": 46,
      "instance": null,
      "seed": 196930371,
      "budget": null,
      "cost": 0.9884643969385731,
      "time": 0.0,
      "cpu_time": 0.0,
      "status": 1,
      "starttime": 1781223322.8353012,
      "endtime": 1781223322.8363006,
      "additional_info": {}
    },
    {
      "config_id": 47,
      "instance": null,
      "seed": 196930371,
      "budget": null,
      "cost": 1.064952493004018,
      "time": 0.0,
      "cpu_time": 0.0,
      "status": 1,
      "starttime": 1781223322.8545988,
      "endtime": 1781223322.8565915,
      "additional_info": {}
    },
    {
      "config_id": 48,
      "instance": null,
      "seed": 196930371,
      "budget": null,
      "cost": 0.7347029111461332,
      "time": 0.0,
      "cpu_time": 0.0,
      "status": 1,
      "starttime": 1781223322.8739822,
      "endtime": 1781223322.876882,
      "additional_info": {}
    },
    {
      "config_id": 49,
      "instance": null,
      "seed": 196930371,
      "budget": null,
      "cost": 0.7407504878384543,
      "time": 0.0,
      "cpu_time": 0.0,
      "status": 1,
      "starttime": 1781223322.8954117,
      "endtime": 1781223322.8974147,
      "additional_info": {}
    },
    {
      "config_id": 50,
      "instance": null,
      "seed": 196930371,
      "budget": null,
      "cost": 0.6526235730517094,
      "time": 0.0,
      "cpu_time": 0.0,
      "status": 1,
      "starttime": 1781223322.9152734,
      "endtime": 1781223322.9172723,
      "additional_info": {}
    },
    {
      "config_id": 51,
      "instance": null,
      "seed": 196930371,
      "budget": null,
      "cost": 0.5544556366518094,
      "time": 0.0,
      "cpu_time": 0.0,
      "status": 1,
      "starttime": 1781223328.1497493,
      "endtime": 1781223328.1518433,
      "additional_info": {}
    },
    {
      "config_id": 52,
      "instance": null,
      "seed": 196930371,
      "budget": null,
      "cost": 0.5278624753597221,
      "time": 0.0,
      "cpu_time": 0.0,
      "status": 1,
      "starttime": 1781223328.1678412,
      "endtime": 1781223328.168834,
      "additional_info": {}
    },
    {
      "config_id": 53,
      "instance": null,
      "seed": 196930371,
      "budget": null,
      "cost": 0.5461924574616273,
      "time": 0.0,
      "cpu_time": 0.0,
      "status": 1,
      "starttime": 1781223328.1838539,
      "endtime": 1781223328.1859722,
      "additional_info": {}
    },
    {
      "config_id": 54,
      "instance": null,
      "seed": 196930371,
      "budget": null,
      "cost": 0.5340718944346321,
      "time": 0.0,
      "cpu_time": 0.0,
      "status": 1,
      "starttime": 1781223328.2014036,
      "endtime": 1781223328.2024121,
      "additional_info": {}
    },
    {
      "config_id": 55,
      "instance": null,
      "seed": 196930371,
      "budget": null,
      "cost": 52.148951103694124,
      "time": 0.0,
      "cpu_time": 0.0,
      "status": 1,
      "starttime": 1781223328.2159464,
      "endtime": 1781223328.2169564,
      "additional_info": {}
    },
    {
      "config_id": 56,
      "instance": null,
      "seed": 196930371,
      "budget": null,
      "cost": 0.5172536784026409,
      "time": 0.0010323524475097656,
      "cpu_time": 0.0,
      "status": 1,
      "starttime": 1781223328.2278538,
      "endtime": 1781223328.2299883,
      "additional_info": {}
    },
    {
      "config_id": 57,
      "instance": null,
      "seed": 196930371,
      "budget": null,
      "cost": 0.5332193681068276,
      "time": 0.0,
      "cpu_time": 0.0,
      "status": 1,
      "starttime": 1781223328.2438543,
      "endtime": 1781223328.24587,
      "additional_info": {}
    },
    {
      "config_id": 58,
      "instance": null,
      "seed": 196930371,
      "budget": null,
      "cost": 27.30691654058706,
      "time": 0.0,
      "cpu_time": 0.0,
      "status": 1,
      "starttime": 1781223328.2642713,
      "endtime": 1781223328.2662458,
      "additional_info": {}
    },
    {
      "config_id": 59,
      "instance": null,
      "seed": 196930371,
      "budget": null,
      "cost": 0.4711004103418013,
      "time": 0.0,
      "cpu_time": 0.0,
      "status": 1,
      "starttime": 1781223333.4714024,
      "endtime": 1781223333.4734006,
      "additional_info": {}
    },
    {
      "config_id": 60,
      "instance": null,
      "seed": 196930371,
      "budget": null,
      "cost": 0.4671291145286247,
      "time": 0.0,
      "cpu_time": 0.0,
      "status": 1,
      "starttime": 1781223333.4997094,
      "endtime": 1781223333.501912,
      "additional_info": {}
    },
    {
      "config_id": 61,
      "instance": null,
      "seed": 196930371,
      "budget": null,
      "cost": 0.4732434146107991,
      "time": 0.0010030269622802734,
      "cpu_time": 0.0,
      "status": 1,
      "starttime": 1781223333.520481,
      "endtime": 1781223333.5224676,
      "additional_info": {}
    },
    {
      "config_id": 62,
      "instance": null,
      "seed": 196930371,
      "budget": null,
      "cost": 0.46671600145624126,
      "time": 0.0,
      "cpu_time": 0.0,
      "status": 1,
      "starttime": 1781223333.5363696,
      "endtime": 1781223333.5373714,
      "additional_info": {}
    },
    {
      "config_id": 63,
      "instance": null,
      "seed": 196930371,
      "budget": null,
      "cost": 0.472950292744418,
      "time": 0.0,
      "cpu_time": 0.0,
      "status": 1,
      "starttime": 1781223333.5564327,
      "endtime": 1781223333.5584342,
      "additional_info": {}
    },
    {
      "config_id": 64,
      "instance": null,
      "seed": 196930371,
      "budget": null,
      "cost": 0.4720566070753911,
      "time": 0.0,
      "cpu_time": 0.0,
      "status": 1,
      "starttime": 1781223333.5735402,
      "endtime": 1781223333.5744205,
      "additional_info": {}
    },
    {
      "config_id": 65,
      "instance": null,
      "seed": 196930371,
      "budget": null,
      "cost": 80.20958381309823,
      "time": 0.0,
      "cpu_time": 0.0,
      "status": 1,
      "starttime": 1781223333.5896533,
      "endtime": 1781223333.590651,
      "additional_info": {}
    },
    {
      "config_id": 66,
      "instance": null,
      "seed": 196930371,
      "budget": null,
      "cost": 0.47365144753167066,
      "time": 0.0,
      "cpu_time": 0.0,
      "status": 1,
      "starttime": 1781223333.6046603,
      "endtime": 1781223333.6056492,
      "additional_info": {}
    },
    {
      "config_id": 67,
      "instance": null,
      "seed": 196930371,
      "budget": null,
      "cost": 84.32400564282536,
      "time": 0.0,
      "cpu_time": 0.0,
      "status": 1,
      "starttime": 1781223336.5925548,
      "endtime": 1781223336.595454,
      "additional_info": {}
    },
    {
      "config_id": 68,
      "instance": null,
      "seed": 196930371,
      "budget": null,
      "cost": 30.81568370952311,
      "time": 0.000997304916381836,
      "cpu_time": 0.0,
      "status": 1,
      "starttime": 1781223339.127176,
      "endtime": 1781223339.1291733,
      "additional_info": {}
    },
    {
      "config_id": 69,
      "instance": null,
      "seed": 196930371,
      "budget": null,
      "cost": 33.098102396318254,
      "time": 0.0009877681732177734,
      "cpu_time": 0.0,
      "status": 1,
      "starttime": 1781223339.1535907,
      "endtime": 1781223339.155585,
      "additional_info": {}
    },
    {
      "config_id": 70,
      "instance": null,
      "seed": 196930371,
      "budget": null,
      "cost": 0.49699710672890873,
      "time": 0.0,
      "cpu_time": 0.0,
      "status": 1,
      "starttime": 1781223339.1718235,
      "endtime": 1781223339.1738236,
      "additional_info": {}
    },
    {
      "config_id": 71,
      "instance": null,
      "seed": 196930371,
      "budget": null,
      "cost": 0.6483851737170117,
      "time": 0.0,
      "cpu_time": 0.0,
      "status": 1,
      "starttime": 1781223339.1960833,
      "endtime": 1781223339.1980817,
      "additional_info": {}
    },
    {
      "config_id": 72,
      "instance": null,
      "seed": 196930371,
      "budget": null,
      "cost": 25.460326335559575,
      "time": 0.0,
      "cpu_time": 0.0,
      "status": 1,
      "starttime": 1781223339.2213004,
      "endtime": 1781223339.223311,
      "additional_info": {}
    },
    {
      "config_id": 73,
      "instance": null,
      "seed": 196930371,
      "budget": null,
      "cost": 25.923616434956827,
      "time": 0.0,
      "cpu_time": 0.0,
      "status": 1,
      "starttime": 1781223339.2482185,
      "endtime": 1781223339.250216,
      "additional_info": {}
    },
    {
      "config_id": 74,
      "instance": null,
      "seed": 196930371,
      "budget": null,
      "cost": 0.5341342233375972,
      "time": 0.0,
      "cpu_time": 0.0,
      "status": 1,
      "starttime": 1781223339.2732918,
      "endtime": 1781223339.275284,
      "additional_info": {}
    },
    {
      "config_id": 75,
      "instance": null,
      "seed": 196930371,
      "budget": null,
      "cost": 0.46325835699480145,
      "time": 0.0,
      "cpu_time": 0.0,
      "status": 1,
      "starttime": 1781223344.9421916,
      "endtime": 1781223344.9452918,
      "additional_info": {}
    }
  ],
  "configs": {
    "1": {
      "x1": -0.7264143740758,
      "x2": 5.2019476890564
    },
    "2": {
      "x1": 7.7818373404443,
      "x2": 7.9501295881346
    },
    "3": {
      "x1": 5.8269037120044,
      "x2": 0.2254193276167
    },
    "4": {
      "x1": -2.5362431770191,
      "x2": 12.9313249932602
    },
    "5": {
      "x1": -3.381362631917,
      "x2": 3.4961268072948
    },
    "6": {
      "x1": 3.0467493506148,
      "x2": 13.404181106016
    },
    "7": {
      "x1": 8.8114282907918,
      "x2": 5.6665929174051
    },
    "8": {
      "x1": 2.1182630956173,
      "x2": 11.2419225554913
    },
    "9": {
      "x1": 1.0297508863732,
      "x2": 1.4280392741784
    },
    "10": {
      "x1": 9.3049481976777,
      "x2": 11.6725726705045
    },
    "11": {
      "x1": 3.8331226725131,
      "x2": 3.9404919510707
    },
    "12": {
      "x1": -4.7629571380094,
      "x2": 9.1500742267817
    },
    "13": {
      "x1": -1.8597180489451,
      "x2": 7.2185515612364
    },
    "14": {
      "x1": 4.8042092239484,
      "x2": 9.6302820788696
    },
    "15": {
      "x1": 6.583476937376,
      "x2": 1.885330080986
    },
    "16": {
      "x1": 0.1260055508465,
      "x2": 14.957012613304
    },
    "17": {
      "x1": 0.2287833439186,
      "x2": 2.528829658404
    },
    "18": {
      "x1": 6.9512372836471,
      "x2": 14.3119073985144
    },
    "19": {
      "x1": -2.3543358877742,
      "x2": 12.3029496119365
    },
    "20": {
      "x1": -2.4662779702216,
      "x2": 12.3035418513625
    },
    "21": {
      "x1": -2.7431265298227,
      "x2": 12.3170928633017
    },
    "22": {
      "x1": -2.5456246629914,
      "x2": 12.3021526396254
    },
    "23": {
      "x1": 3.5881585702186,
      "x2": 5.8188898319217
    },
    "24": {
      "x1": -2.7195657816183,
      "x2": 12.3055557130822
    },
    "25": {
      "x1": -2.5310475743681,
      "x2": 12.3117718099122
    },
    "26": {
      "x1": -2.7113229596429,
      "x2": 12.3173713873119
    },
    "27": {
      "x1": -3.7199494611025,
      "x2": 12.4792964834361
    },
    "28": {
      "x1": 7.6064656814779,
      "x2": 5.1659902393048
    },
    "29": {
      "x1": -2.356009994483,
      "x2": 12.3782102007366
    },
    "30": {
      "x1": -4.7170422879149,
      "x2": 12.3128653158366
    },
    "31": {
      "x1": -4.4384158524965,
      "x2": 12.5764168628392
    },
    "32": {
      "x1": -4.0560732831642,
      "x2": 12.582769210122
    },
    "33": {
      "x1": 3.0674546996026,
      "x2": 2.8642597330874
    },
    "34": {
      "x1": -3.2338399049732,
      "x2": 12.747818145587
    },
    "35": {
      "x1": -4.1056148822611,
      "x2": 11.9781346525104
    },
    "36": {
      "x1": -2.4890034954944,
      "x2": 12.0605624761477
    },
    "37": {
      "x1": -2.6769071170373,
      "x2": 2.0730506171894
    },
    "38": {
      "x1": -4.2209847471857,
      "x2": 3.7945870303641
    },
    "39": {
      "x1": -4.5836261833068,
      "x2": 0.6653474371852
    },
    "40": {
      "x1": -3.0654977765187,
      "x2": 11.6540718145612
    },
    "41": {
      "x1": -2.3104103383734,
      "x2": 0.4214719456923
    },
    "42": {
      "x1": -4.0272585051228,
      "x2": 12.3541069228432
    },
    "43": {
      "x1": -3.1615861667534,
      "x2": 12.9947196776689
    },
    "44": {
      "x1": -3.21757403264,
      "x2": 13.1097696710203
    },
    "45": {
      "x1": -3.1928810696039,
      "x2": 13.1327811221982
    },
    "46": {
      "x1": -3.1809714788233,
      "x2": 13.1334685624115
    },
    "47": {
      "x1": -3.1569302439794,
      "x2": 13.1279391590606
    },
    "48": {
      "x1": -3.2501735608923,
      "x2": 13.0668720481686
    },
    "49": {
      "x1": -3.3015241088534,
      "x2": 13.1320435692984
    },
    "50": {
      "x1": -3.2807798364444,
      "x2": 13.0143398648602
    },
    "51": {
      "x1": -3.2515831307893,
      "x2": 12.8548136639892
    },
    "52": {
      "x1": -3.2511300764178,
      "x2": 12.8089182167312
    },
    "53": {
      "x1": -3.2558611519048,
      "x2": 12.8440205311853
    },
    "54": {
      "x1": -3.2547728890774,
      "x2": 12.8220580615194
    },
    "55": {
      "x1": 4.4057250543325,
      "x2": 8.2073490623802
    },
    "56": {
      "x1": -3.252196749002,
      "x2": 12.7887491490362
    },
    "57": {
      "x1": -3.2392265364814,
      "x2": 12.810206460492
    },
    "58": {
      "x1": -0.691641858861,
      "x2": 4.0143470663424
    },
    "59": {
      "x1": -3.230238114559,
      "x2": 12.6774949530211
    },
    "60": {
      "x1": -3.2314984520117,
      "x2": 12.6666393213459
    },
    "61": {
      "x1": -3.2300100766757,
      "x2": 12.6830426903264
    },
    "62": {
      "x1": -3.2322440679277,
      "x2": 12.6653891187019
    },
    "63": {
      "x1": -3.2304311640018,
      "x2": 12.6823838976823
    },
    "64": {
      "x1": -3.236432112079,
      "x2": 12.6802043022469
    },
    "65": {
      "x1": 7.9407509687048,
      "x2": 9.9363237868418
    },
    "66": {
      "x1": -3.2296921720688,
      "x2": 12.6840039372931
    },
    "67": {
      "x1": -1.8415269857895,
      "x2": 0.6001689120561
    },
    "68": {
      "x1": -4.9233718283425,
      "x2": 12.6307191248486
    },
    "69": {
      "x1": -4.9889161077008,
      "x2": 12.6303122664516
    },
    "70": {
      "x1": -3.1579888528166,
      "x2": 12.6271991516056
    },
    "71": {
      "x1": -3.0863300350307,
      "x2": 12.6282181226997
    },
    "72": {
      "x1": -4.7589224360168,
      "x2": 12.6249986644291
    },
    "73": {
      "x1": -4.7738205506446,
      "x2": 12.6259242193372
    },
    "74": {
      "x1": -3.3084559755815,
      "x2": 12.6259515992934
    },
    "75": {
      "x1": -3.2324535780163,
      "x2": 12.6549329830686
    }
  },
  "config_origins": {
    "1": "Initial Design: Sobol",
    "2": "Initial Design: Sobol",
    "3": "Initial Design: Sobol",
    "4": "Initial Design: Sobol",
    "5": "Initial Design: Sobol",
    "6": "Initial Design: Sobol",
    "7": "Initial Design: Sobol",
    "8": "Initial Design: Sobol",
    "9": "Initial Design: Sobol",
    "10": "Initial Design: Sobol",
    "11": "Initial Design: Sobol",
    "12": "Initial Design: Sobol",
    "13": "Initial Design: Sobol",
    "14": "Initial Design: Sobol",
    "15": "Initial Design: Sobol",
    "16": "Initial Design: Sobol",
    "17": "Initial Design: Sobol",
    "18": "Initial Design: Sobol",
    "19": "Acquisition Function Maximizer: Local Search",
    "20": "Acquisition Function Maximizer: Local Search",
    "21": "Acquisition Function Maximizer: Local Search",
    "22": "Acquisition Function Maximizer: Local Search",
    "23": "Random Search",
    "24": "Acquisition Function Maximizer: Local Search",
    "25": "Acquisition Function Maximizer: Local Search",
    "26": "Acquisition Function Maximizer: Local Search",
    "27": "Acquisition Function Maximizer: Local Search",
    "28": "Random Search",
    "29": "Acquisition Function Maximizer: Local Search",
    "30": "Acquisition Function Maximizer: Local Search",
    "31": "Acquisition Function Maximizer: Local Search",
    "32": "Acquisition Function Maximizer: Local Search",
    "33": "Random Search",
    "34": "Acquisition Function Maximizer: Local Search",
    "35": "Acquisition Function Maximizer: Local Search",
    "36": "Random Search",
    "37": "Acquisition Function Maximizer: Local Search",
    "38": "Acquisition Function Maximizer: Local Search",
    "39": "Random Search",
    "40": "Acquisition Function Maximizer: Local Search",
    "41": "Acquisition Function Maximizer: Local Search",
    "42": "Acquisition Function Maximizer: Local Search",
    "43": "Acquisition Function Maximizer: Local Search",
    "44": "Acquisition Function Maximizer: Local Search",
    "45": "Acquisition Function Maximizer: Local Search",
    "46": "Acquisition Function Maximizer: Local Search",
    "47": "Acquisition Function Maximizer: Local Search",
    "48": "Acquisition Function Maximizer: Local Search",
    "49": "Acquisition Function Maximizer: Local Search",
    "50": "Acquisition Function Maximizer: Local Search",
    "51": "Acquisition Function Maximizer: Local Search",
    "52": "Acquisition Function Maximizer: Local Search",
    "53": "Acquisition Function Maximizer: Local Search",
    "54": "Acquisition Function Maximizer: Local Search",
    "55": "Random Search",
    "56": "Acquisition Function Maximizer: Local Search",
    "57": "Acquisition Function Maximizer: Local Search",
    "58": "Random Search",
    "59": "Acquisition Function Maximizer: Local Search",
    "60": "Acquisition Function Maximizer: Local Search",
    "61": "Acquisition Function Maximizer: Local Search",
    "62": "Acquisition Function Maximizer: Local Search",
    "63": "Acquisition Function Maximizer: Local Search",
    "64": "Acquisition Function Maximizer: Local Search",
    "65": "Random Search",
    "66": "Acquisition Function Maximizer: Local Search",
    "67": "Random Search",
    "68": "Acquisition Function Maximizer: Local Search",
    "69": "Acquisition Function Maximizer: Local Search",
    "70": "Acquisition Function Maximizer: Local Search",
    "71": "Acquisition Function Maximizer: Local Search",
    "72": "Acquisition Function Maximizer: Local Search",
    "73": "Acquisition Function Maximizer: Local Search",
    "74": "Acquisition Function Maximizer: Local Search",
    "75": "Acquisition Function Maximizer: Local Search"
  }
}