{
  "seed": 4,
  "policy": [
    3,
    5,
    3,
    3
  ],
  "policy_name": "leaf_policy_3_5_3_3",
  "n_trials": 400,
  "trials_per_block": 100,
  "n_initial_design_configs": 25,
  "final_incumbent_cost": -3.3204171252793504,
  "milestone_best_costs": {
    "100": -3.118014520231898,
    "200": -3.2299824289405783,
    "300": -3.3183304294856617,
    "400": -3.3204171252793504
  },
  "incumbent": {
    "x1": 0.1943820973973,
    "x2": 0.1461249974515,
    "x3": 0.4802923875614,
    "x4": 0.2752123110985,
    "x5": 0.3114143297071,
    "x6": 0.6508438813351
  },
  "run_dir": "/home/io632776/experiments/adaptive-smac/experiments/hartmann/06_brute_force_leaf_size/hartmann_6d_bruteforce_leaf_policies_400_trials_leaf_1_2_3_5/leaf_policy_3_5_3_3/4"
}