{
  "seed": 4,
  "policy": [
    1,
    2,
    2,
    1
  ],
  "policy_name": "leaf_policy_1_2_2_1",
  "n_trials": 400,
  "trials_per_block": 100,
  "n_initial_design_configs": 25,
  "final_incumbent_cost": -3.2389291333656516,
  "milestone_best_costs": {
    "100": -2.759084145315605,
    "200": -3.1511469226446867,
    "300": -3.1974752494858163,
    "400": -3.2389291333656516
  },
  "incumbent": {
    "x1": 0.1457938058539,
    "x2": 0.1860494872085,
    "x3": 0.4637828815438,
    "x4": 0.2940285673885,
    "x5": 0.2947284971871,
    "x6": 0.6681647402018
  },
  "run_dir": "/home/io632776/experiments/adaptive-smac/experiments/hartmann/06_brute_force_leaf_size/hartmann_6d_bruteforce_leaf_policies_400_trials_leaf_1_2_3_5/leaf_policy_1_2_2_1/4"
}