{
  "seed": 1,
  "policy": [
    1,
    1,
    2,
    1
  ],
  "policy_name": "leaf_policy_1_1_2_1",
  "n_trials": 400,
  "trials_per_block": 100,
  "n_initial_design_configs": 25,
  "final_incumbent_cost": -3.143096987522793,
  "milestone_best_costs": {
    "100": -2.9558627947156753,
    "200": -3.140403760908415,
    "300": -3.1429742960516176,
    "400": -3.143096987522793
  },
  "incumbent": {
    "x1": 0.4044014946568,
    "x2": 0.8830536088841,
    "x3": 0.8433571577474,
    "x4": 0.5742487536381,
    "x5": 0.1359671286807,
    "x6": 0.0016554157478
  },
  "run_dir": "/home/io632776/experiments/adaptive-smac/experiments/hartmann/06_brute_force_leaf_size/hartmann_6d_bruteforce_leaf_policies_400_trials_leaf_1_2_3_5/leaf_policy_1_1_2_1/1"
}