{
  "seed": 1,
  "policy": [
    2,
    3,
    5,
    3
  ],
  "policy_name": "leaf_policy_2_3_5_3",
  "n_trials": 400,
  "trials_per_block": 100,
  "n_initial_design_configs": 25,
  "final_incumbent_cost": -3.2013990406685,
  "milestone_best_costs": {
    "100": -3.0963960030261033,
    "200": -3.183232619435966,
    "300": -3.1993295944140288,
    "400": -3.2013990406685
  },
  "incumbent": {
    "x1": 0.4054882723975,
    "x2": 0.8869555924257,
    "x3": 0.8585479315337,
    "x4": 0.5796730571112,
    "x5": 0.1184947910343,
    "x6": 0.0373152556801
  },
  "run_dir": "/home/io632776/experiments/adaptive-smac/experiments/hartmann/06_brute_force_leaf_size/hartmann_6d_bruteforce_leaf_policies_400_trials_leaf_1_2_3_5/leaf_policy_2_3_5_3/1"
}