{
  "seed": 0,
  "policy": [
    3,
    5,
    1,
    5
  ],
  "policy_name": "leaf_policy_3_5_1_5",
  "n_trials": 400,
  "trials_per_block": 100,
  "n_initial_design_configs": 25,
  "final_incumbent_cost": -3.1979274686931523,
  "milestone_best_costs": {
    "100": -3.0398214878314107,
    "200": -3.122566225416322,
    "300": -3.1943489536122125,
    "400": -3.1979274686931523
  },
  "incumbent": {
    "x1": 0.4042736615381,
    "x2": 0.8738519650134,
    "x3": 0.9851223040089,
    "x4": 0.5736238030613,
    "x5": 0.097370525916,
    "x6": 0.0378993457577
  },
  "run_dir": "/home/io632776/experiments/adaptive-smac/experiments/hartmann/06_brute_force_leaf_size/hartmann_6d_bruteforce_leaf_policies_400_trials_leaf_1_2_3_5/leaf_policy_3_5_1_5/0"
}