{
  "seed": 3,
  "policy": [
    5,
    1,
    3,
    2
  ],
  "policy_name": "leaf_policy_5_1_3_2",
  "n_trials": 400,
  "trials_per_block": 100,
  "n_initial_design_configs": 25,
  "final_incumbent_cost": -3.1903728980849024,
  "milestone_best_costs": {
    "100": -2.1201493732500913,
    "200": -3.144652758831762,
    "300": -3.1702613678419636,
    "400": -3.1903728980849024
  },
  "incumbent": {
    "x1": 0.4042640536563,
    "x2": 0.8765516787515,
    "x3": 0.8865644259215,
    "x4": 0.5825697903215,
    "x5": 0.0249052879309,
    "x6": 0.0494020654011
  },
  "run_dir": "/home/io632776/experiments/adaptive-smac/experiments/hartmann/06_brute_force_leaf_size/hartmann_6d_bruteforce_leaf_policies_400_trials_leaf_1_2_3_5/leaf_policy_5_1_3_2/3"
}