{
  "seed": 0,
  "policy": [
    1,
    1,
    5,
    1
  ],
  "policy_name": "leaf_policy_1_1_5_1",
  "n_trials": 400,
  "trials_per_block": 100,
  "n_initial_design_configs": 25,
  "final_incumbent_cost": -3.1847309819789476,
  "milestone_best_costs": {
    "100": -2.988438161772009,
    "200": -3.104304008997378,
    "300": -3.1591461500428615,
    "400": -3.1847309819789476
  },
  "incumbent": {
    "x1": 0.4057801555796,
    "x2": 0.8806363271827,
    "x3": 0.8762845135324,
    "x4": 0.5848176647112,
    "x5": 0.0298480194908,
    "x6": 0.0225551246982
  },
  "run_dir": "/home/io632776/experiments/adaptive-smac/experiments/hartmann/06_brute_force_leaf_size/hartmann_6d_bruteforce_leaf_policies_400_trials_leaf_1_2_3_5/leaf_policy_1_1_5_1/0"
}