{
  "seed": 4,
  "policy": [
    3,
    1,
    2,
    3
  ],
  "policy_name": "leaf_policy_3_1_2_3",
  "n_trials": 400,
  "trials_per_block": 100,
  "n_initial_design_configs": 25,
  "final_incumbent_cost": -3.298256049517627,
  "milestone_best_costs": {
    "100": -3.118014520231898,
    "200": -3.2286932881782855,
    "300": -3.2932373317085437,
    "400": -3.298256049517627
  },
  "incumbent": {
    "x1": 0.1921622885546,
    "x2": 0.15308816534,
    "x3": 0.4426270383499,
    "x4": 0.2582704260196,
    "x5": 0.3158860622786,
    "x6": 0.6616066397471
  },
  "run_dir": "/home/io632776/experiments/adaptive-smac/experiments/hartmann/06_brute_force_leaf_size/hartmann_6d_bruteforce_leaf_policies_400_trials_leaf_1_2_3_5/leaf_policy_3_1_2_3/4"
}