{
  "seed": 1,
  "policy": [
    2,
    3,
    1,
    2
  ],
  "policy_name": "leaf_policy_2_3_1_2",
  "n_trials": 400,
  "trials_per_block": 100,
  "n_initial_design_configs": 25,
  "final_incumbent_cost": -3.1988983586187887,
  "milestone_best_costs": {
    "100": -3.1161686855050195,
    "200": -3.1948165484001803,
    "300": -3.198547896709704,
    "400": -3.1988983586187887
  },
  "incumbent": {
    "x1": 0.4057658683069,
    "x2": 0.8840272775608,
    "x3": 0.8539850471155,
    "x4": 0.5744223802481,
    "x5": 0.0218043257201,
    "x6": 0.0376292479951
  },
  "run_dir": "/home/io632776/experiments/adaptive-smac/experiments/hartmann/06_brute_force_leaf_size/hartmann_6d_bruteforce_leaf_policies_400_trials_leaf_1_2_3_5/leaf_policy_2_3_1_2/1"
}