{
  "seed": 0,
  "policy": [
    5,
    2,
    3,
    2
  ],
  "policy_name": "leaf_policy_5_2_3_2",
  "n_trials": 400,
  "trials_per_block": 100,
  "n_initial_design_configs": 25,
  "final_incumbent_cost": -3.1995969747035935,
  "milestone_best_costs": {
    "100": -3.0773102957961593,
    "200": -3.1620869233568865,
    "300": -3.1994520832953084,
    "400": -3.1995969747035935
  },
  "incumbent": {
    "x1": 0.4049226690147,
    "x2": 0.8868101510743,
    "x3": 0.8633917703001,
    "x4": 0.5721738968658,
    "x5": 0.1633910683615,
    "x6": 0.0307352634633
  },
  "run_dir": "/home/io632776/experiments/adaptive-smac/experiments/hartmann/06_brute_force_leaf_size/hartmann_6d_bruteforce_leaf_policies_400_trials_leaf_1_2_3_5/leaf_policy_5_2_3_2/0"
}