{
  "seed": 2,
  "policy": [
    2,
    1,
    5,
    2
  ],
  "policy_name": "leaf_policy_2_1_5_2",
  "n_trials": 400,
  "trials_per_block": 100,
  "n_initial_design_configs": 25,
  "final_incumbent_cost": -3.19964282821716,
  "milestone_best_costs": {
    "100": -1.7439976668115074,
    "200": -3.182700796174918,
    "300": -3.197520406406668,
    "400": -3.19964282821716
  },
  "incumbent": {
    "x1": 0.4119444420086,
    "x2": 0.8819281476816,
    "x3": 0.8021731954361,
    "x4": 0.5744457400837,
    "x5": 0.1624919720422,
    "x6": 0.0405402375815
  },
  "run_dir": "/home/io632776/experiments/adaptive-smac/experiments/hartmann/06_brute_force_leaf_size/hartmann_6d_bruteforce_leaf_policies_400_trials_leaf_1_2_3_5/leaf_policy_2_1_5_2/2"
}