{
  "stats": {
    "submitted": 20,
    "finished": 20,
    "running": 0
  },
  "data": [
    {
      "config_id": 1,
      "instance": null,
      "seed": 209652396,
      "budget": null,
      "cost": 5.4345623938566385,
      "time": 6.9141387939453125e-06,
      "cpu_time": 5.927000000127691e-06,
      "status": 1,
      "starttime": 1781708705.928523,
      "endtime": 1781708705.929085,
      "additional_info": {}
    },
    {
      "config_id": 2,
      "instance": null,
      "seed": 209652396,
      "budget": null,
      "cost": 4.669372941395943,
      "time": 3.814697265625e-06,
      "cpu_time": 3.2789999999671693e-06,
      "status": 1,
      "starttime": 1781708705.9305212,
      "endtime": 1781708705.9309266,
      "additional_info": {}
    },
    {
      "config_id": 3,
      "instance": null,
      "seed": 209652396,
      "budget": null,
      "cost": 11.308277547006911,
      "time": 4.0531158447265625e-06,
      "cpu_time": 3.1190000000513862e-06,
      "status": 1,
      "starttime": 1781708705.9324512,
      "endtime": 1781708705.9328606,
      "additional_info": {}
    },
    {
      "config_id": 4,
      "instance": null,
      "seed": 209652396,
      "budget": null,
      "cost": 12.612945606144095,
      "time": 4.5299530029296875e-06,
      "cpu_time": 3.6569999999347402e-06,
      "status": 1,
      "starttime": 1781708705.934222,
      "endtime": 1781708705.9346058,
      "additional_info": {}
    },
    {
      "config_id": 5,
      "instance": null,
      "seed": 209652396,
      "budget": null,
      "cost": 16.09908332897719,
      "time": 4.291534423828125e-06,
      "cpu_time": 3.389999999825477e-06,
      "status": 1,
      "starttime": 1781708705.9359252,
      "endtime": 1781708705.936314,
      "additional_info": {}
    },
    {
      "config_id": 6,
      "instance": null,
      "seed": 209652396,
      "budget": null,
      "cost": 0.24818338849520738,
      "time": 4.76837158203125e-06,
      "cpu_time": 4.101999999894801e-06,
      "status": 1,
      "starttime": 1781708706.2622733,
      "endtime": 1781708706.262674,
      "additional_info": {}
    },
    {
      "config_id": 7,
      "instance": null,
      "seed": 209652396,
      "budget": null,
      "cost": 0.08895554948789221,
      "time": 3.337860107421875e-06,
      "cpu_time": 2.783999999866893e-06,
      "status": 1,
      "starttime": 1781708706.264553,
      "endtime": 1781708706.2649171,
      "additional_info": {}
    },
    {
      "config_id": 8,
      "instance": null,
      "seed": 209652396,
      "budget": null,
      "cost": 5.5610181275992296e-05,
      "time": 3.337860107421875e-06,
      "cpu_time": 2.7289999999791092e-06,
      "status": 1,
      "starttime": 1781708706.266487,
      "endtime": 1781708706.2668464,
      "additional_info": {}
    },
    {
      "config_id": 9,
      "instance": null,
      "seed": 209652396,
      "budget": null,
      "cost": 0.24716107180633046,
      "time": 3.337860107421875e-06,
      "cpu_time": 2.7659999999318785e-06,
      "status": 1,
      "starttime": 1781708706.268437,
      "endtime": 1781708706.2687988,
      "additional_info": {}
    },
    {
      "config_id": 10,
      "instance": null,
      "seed": 209652396,
      "budget": null,
      "cost": 0.10506978595203639,
      "time": 3.0994415283203125e-06,
      "cpu_time": 2.336999999963396e-06,
      "status": 1,
      "starttime": 1781708706.2704546,
      "endtime": 1781708706.270813,
      "additional_info": {}
    },
    {
      "config_id": 11,
      "instance": null,
      "seed": 209652396,
      "budget": null,
      "cost": 0.21663274288434564,
      "time": 3.5762786865234375e-06,
      "cpu_time": 2.924999999986966e-06,
      "status": 1,
      "starttime": 1781708706.272421,
      "endtime": 1781708706.272839,
      "additional_info": {}
    },
    {
      "config_id": 12,
      "instance": null,
      "seed": 209652396,
      "budget": null,
      "cost": 0.015541080690418655,
      "time": 3.5762786865234375e-06,
      "cpu_time": 2.8780000000949713e-06,
      "status": 1,
      "starttime": 1781708706.2744749,
      "endtime": 1781708706.2748349,
      "additional_info": {}
    },
    {
      "config_id": 13,
      "instance": null,
      "seed": 209652396,
      "budget": null,
      "cost": 0.004490857255397455,
      "time": 3.337860107421875e-06,
      "cpu_time": 2.7360000001142026e-06,
      "status": 1,
      "starttime": 1781708706.2764752,
      "endtime": 1781708706.2768369,
      "additional_info": {}
    },
    {
      "config_id": 14,
      "instance": null,
      "seed": 209652396,
      "budget": null,
      "cost": 1.289919263279842,
      "time": 9.5367431640625e-06,
      "cpu_time": 8.926999999658847e-06,
      "status": 1,
      "starttime": 1781708706.7932923,
      "endtime": 1781708706.7938821,
      "additional_info": {}
    },
    {
      "config_id": 15,
      "instance": null,
      "seed": 209652396,
      "budget": null,
      "cost": 1.2878217064087212,
      "time": 9.775161743164062e-06,
      "cpu_time": 8.659000000132977e-06,
      "status": 1,
      "starttime": 1781708706.7969131,
      "endtime": 1781708706.797441,
      "additional_info": {}
    },
    {
      "config_id": 16,
      "instance": null,
      "seed": 209652396,
      "budget": null,
      "cost": 1.3477430545922888,
      "time": 5.4836273193359375e-06,
      "cpu_time": 4.904999999943982e-06,
      "status": 1,
      "starttime": 1781708706.7998688,
      "endtime": 1781708706.8003998,
      "additional_info": {}
    },
    {
      "config_id": 17,
      "instance": null,
      "seed": 209652396,
      "budget": null,
      "cost": 1.2862655026006686,
      "time": 7.3909759521484375e-06,
      "cpu_time": 6.552999999964726e-06,
      "status": 1,
      "starttime": 1781708706.8027308,
      "endtime": 1781708706.8031933,
      "additional_info": {}
    },
    {
      "config_id": 18,
      "instance": null,
      "seed": 209652396,
      "budget": null,
      "cost": 1.2896335732360686,
      "time": 7.62939453125e-06,
      "cpu_time": 6.847999999948229e-06,
      "status": 1,
      "starttime": 1781708706.805473,
      "endtime": 1781708706.80596,
      "additional_info": {}
    },
    {
      "config_id": 19,
      "instance": null,
      "seed": 209652396,
      "budget": null,
      "cost": 1.3221696554775444,
      "time": 6.67572021484375e-06,
      "cpu_time": 5.833000000343702e-06,
      "status": 1,
      "starttime": 1781708706.8082411,
      "endtime": 1781708706.8087168,
      "additional_info": {}
    },
    {
      "config_id": 20,
      "instance": null,
      "seed": 209652396,
      "budget": null,
      "cost": 4.960619830336341,
      "time": 5.4836273193359375e-06,
      "cpu_time": 4.746000000110939e-06,
      "status": 1,
      "starttime": 1781708706.8115153,
      "endtime": 1781708706.812026,
      "additional_info": {}
    }
  ],
  "configs": {
    "1": {
      "x": -2.3312147893012
    },
    "2": {
      "x": 2.1608731895685
    },
    "3": {
      "x": 3.3627782482654
    },
    "4": {
      "x": -3.551470907405
    },
    "5": {
      "x": -4.0123663004488
    },
    "6": {
      "x": 0.4981800763732
    },
    "7": {
      "x": 0.2982541692716
    },
    "8": {
      "x": 0.0074572234294
    },
    "9": {
      "x": 0.4971529662049
    },
    "10": {
      "x": 0.324144699096
    },
    "11": {
      "x": 0.4654382267115
    },
    "12": {
      "x": 0.1246638708304
    },
    "13": {
      "x": 0.0670138586816
    },
    "14": {
      "x": -1.1357461262447
    },
    "15": {
      "x": -1.134822323718
    },
    "16": {
      "x": -1.1609233629281
    },
    "17": {
      "x": -1.1341364567814
    },
    "18": {
      "x": -1.1356203473151
    },
    "19": {
      "x": -1.1498563629765
    },
    "20": {
      "x": 2.2272448968033
    }
  },
  "config_origins": {
    "1": "Initial Design: Sobol",
    "2": "Initial Design: Sobol",
    "3": "Initial Design: Sobol",
    "4": "Initial Design: Sobol",
    "5": "Initial Design: Sobol",
    "6": "Acquisition Function Maximizer: Local Search",
    "7": "Acquisition Function Maximizer: Local Search",
    "8": "Acquisition Function Maximizer: Local Search",
    "9": "Acquisition Function Maximizer: Local Search",
    "10": "Acquisition Function Maximizer: Local Search",
    "11": "Acquisition Function Maximizer: Local Search",
    "12": "Acquisition Function Maximizer: Local Search",
    "13": "Acquisition Function Maximizer: Local Search",
    "14": "Acquisition Function Maximizer: Local Search",
    "15": "Acquisition Function Maximizer: Local Search",
    "16": "Acquisition Function Maximizer: Local Search",
    "17": "Acquisition Function Maximizer: Local Search",
    "18": "Acquisition Function Maximizer: Local Search",
    "19": "Acquisition Function Maximizer: Local Search",
    "20": "Random Search"
  }
}