{
  "incumbent_ids": [
    391
  ],
  "rejected_config_ids": [
    2,
    3,
    4,
    5,
    6,
    7,
    8,
    9,
    10,
    11,
    12,
    13,
    1,
    15,
    16,
    17,
    18,
    19,
    20,
    21,
    22,
    23,
    24,
    25,
    26,
    27,
    28,
    29,
    30,
    31,
    32,
    33,
    34,
    35,
    36,
    37,
    38,
    39,
    40,
    41,
    42,
    43,
    44,
    45,
    46,
    14,
    47,
    49,
    50,
    48,
    52,
    51,
    54,
    55,
    56,
    57,
    58,
    59,
    60,
    61,
    62,
    63,
    64,
    65,
    66,
    67,
    68,
    69,
    70,
    71,
    72,
    73,
    74,
    75,
    76,
    77,
    78,
    79,
    80,
    81,
    82,
    83,
    84,
    85,
    86,
    87,
    88,
    89,
    90,
    91,
    92,
    93,
    53,
    95,
    96,
    94,
    98,
    99,
    100,
    101,
    102,
    103,
    104,
    105,
    106,
    97,
    108,
    109,
    110,
    111,
    112,
    113,
    107,
    115,
    116,
    117,
    118,
    119,
    120,
    121,
    114,
    123,
    124,
    125,
    126,
    127,
    128,
    129,
    130,
    131,
    132,
    133,
    122,
    135,
    136,
    137,
    138,
    139,
    140,
    141,
    142,
    143,
    144,
    145,
    146,
    147,
    148,
    149,
    150,
    151,
    152,
    153,
    154,
    155,
    156,
    157,
    158,
    159,
    160,
    161,
    162,
    163,
    164,
    165,
    166,
    167,
    168,
    169,
    170,
    171,
    172,
    173,
    174,
    175,
    176,
    177,
    134,
    179,
    180,
    181,
    182,
    183,
    184,
    185,
    186,
    187,
    188,
    189,
    190,
    191,
    178,
    193,
    192,
    195,
    196,
    197,
    198,
    199,
    200,
    201,
    202,
    203,
    204,
    205,
    206,
    207,
    208,
    209,
    210,
    211,
    212,
    213,
    214,
    215,
    216,
    217,
    194,
    218,
    219,
    221,
    222,
    223,
    224,
    225,
    226,
    227,
    228,
    229,
    230,
    220,
    232,
    233,
    234,
    235,
    231,
    237,
    236,
    239,
    240,
    241,
    242,
    243,
    244,
    245,
    246,
    247,
    248,
    249,
    250,
    251,
    252,
    253,
    238,
    255,
    256,
    257,
    258,
    259,
    260,
    261,
    262,
    263,
    264,
    265,
    266,
    267,
    268,
    269,
    270,
    271,
    272,
    273,
    254,
    275,
    276,
    277,
    278,
    279,
    280,
    281,
    282,
    283,
    284,
    285,
    286,
    287,
    288,
    289,
    290,
    291,
    292,
    293,
    294,
    295,
    296,
    297,
    298,
    299,
    300,
    301,
    302,
    274,
    304,
    305,
    306,
    307,
    303,
    308,
    310,
    311,
    312,
    313,
    314,
    315,
    316,
    317,
    318,
    319,
    320,
    321,
    322,
    323,
    324,
    325,
    326,
    327,
    328,
    329,
    330,
    331,
    332,
    333,
    334,
    335,
    336,
    337,
    338,
    339,
    340,
    341,
    342,
    343,
    344,
    345,
    346,
    347,
    348,
    349,
    350,
    351,
    352,
    353,
    309,
    354,
    356,
    357,
    358,
    359,
    360,
    355,
    362,
    363,
    364,
    365,
    366,
    367,
    368,
    369,
    370,
    371,
    372,
    373,
    374,
    375,
    376,
    377,
    378,
    379,
    380,
    381,
    382,
    383,
    384,
    385,
    386,
    387,
    388,
    389,
    390,
    361,
    392,
    393,
    394,
    395,
    396,
    397,
    398,
    399,
    400
  ],
  "incumbents_changed": 30,
  "trajectory": [
    {
      "config_ids": [
        1
      ],
      "costs": [
        -0.8844801719943094
      ],
      "trial": 1,
      "walltime": 0.0024979114532470703
    },
    {
      "config_ids": [
        14
      ],
      "costs": [
        -1.1629591518362856
      ],
      "trial": 14,
      "walltime": 0.05675363540649414
    },
    {
      "config_ids": [
        47
      ],
      "costs": [
        -1.291407560496738
      ],
      "trial": 47,
      "walltime": 2.4149692058563232
    },
    {
      "config_ids": [
        48
      ],
      "costs": [
        -1.399875144150708
      ],
      "trial": 48,
      "walltime": 2.4240477085113525
    },
    {
      "config_ids": [
        51
      ],
      "costs": [
        -1.8143495582272473
      ],
      "trial": 51,
      "walltime": 3.2649834156036377
    },
    {
      "config_ids": [
        53
      ],
      "costs": [
        -2.803782377123677
      ],
      "trial": 53,
      "walltime": 3.282095432281494
    },
    {
      "config_ids": [
        94
      ],
      "costs": [
        -2.8048163354598343
      ],
      "trial": 94,
      "walltime": 7.961402893066406
    },
    {
      "config_ids": [
        97
      ],
      "costs": [
        -2.8349014005892794
      ],
      "trial": 97,
      "walltime": 8.00434684753418
    },
    {
      "config_ids": [
        107
      ],
      "costs": [
        -2.883105411168028
      ],
      "trial": 107,
      "walltime": 9.944127082824707
    },
    {
      "config_ids": [
        114
      ],
      "costs": [
        -2.9546269176320843
      ],
      "trial": 114,
      "walltime": 10.925017356872559
    },
    {
      "config_ids": [
        122
      ],
      "costs": [
        -2.993479131320876
      ],
      "trial": 122,
      "walltime": 11.926649808883667
    },
    {
      "config_ids": [
        134
      ],
      "costs": [
        -3.015410153631588
      ],
      "trial": 134,
      "walltime": 13.000030517578125
    },
    {
      "config_ids": [
        178
      ],
      "costs": [
        -3.0277219233766903
      ],
      "trial": 178,
      "walltime": 19.93057894706726
    },
    {
      "config_ids": [
        192
      ],
      "costs": [
        -3.0403376329991487
      ],
      "trial": 192,
      "walltime": 21.19530987739563
    },
    {
      "config_ids": [
        194
      ],
      "costs": [
        -3.055610818815486
      ],
      "trial": 194,
      "walltime": 22.318434476852417
    },
    {
      "config_ids": [
        218
      ],
      "costs": [
        -3.056767928306162
      ],
      "trial": 218,
      "walltime": 25.84508776664734
    },
    {
      "config_ids": [
        219
      ],
      "costs": [
        -3.0571074618011087
      ],
      "trial": 219,
      "walltime": 25.87041449546814
    },
    {
      "config_ids": [
        220
      ],
      "costs": [
        -3.060765062584873
      ],
      "trial": 220,
      "walltime": 25.89616298675537
    },
    {
      "config_ids": [
        231
      ],
      "costs": [
        -3.0620140526354884
      ],
      "trial": 231,
      "walltime": 27.126566171646118
    },
    {
      "config_ids": [
        236
      ],
      "costs": [
        -3.063103775521405
      ],
      "trial": 236,
      "walltime": 28.31237506866455
    },
    {
      "config_ids": [
        238
      ],
      "costs": [
        -3.0642637864706974
      ],
      "trial": 238,
      "walltime": 28.364110231399536
    },
    {
      "config_ids": [
        254
      ],
      "costs": [
        -3.0762277893907375
      ],
      "trial": 254,
      "walltime": 30.83224630355835
    },
    {
      "config_ids": [
        274
      ],
      "costs": [
        -3.079393695997516
      ],
      "trial": 274,
      "walltime": 35.01080346107483
    },
    {
      "config_ids": [
        303
      ],
      "costs": [
        -3.0846353986729036
      ],
      "trial": 303,
      "walltime": 39.26263952255249
    },
    {
      "config_ids": [
        308
      ],
      "costs": [
        -3.088262857077404
      ],
      "trial": 308,
      "walltime": 40.44553589820862
    },
    {
      "config_ids": [
        309
      ],
      "costs": [
        -3.0902263675505375
      ],
      "trial": 309,
      "walltime": 40.478556394577026
    },
    {
      "config_ids": [
        354
      ],
      "costs": [
        -3.093054806924115
      ],
      "trial": 354,
      "walltime": 49.05008363723755
    },
    {
      "config_ids": [
        355
      ],
      "costs": [
        -3.0940666859214043
      ],
      "trial": 355,
      "walltime": 49.09019994735718
    },
    {
      "config_ids": [
        361
      ],
      "costs": [
        -3.0949350051183866
      ],
      "trial": 361,
      "walltime": 49.32599472999573
    },
    {
      "config_ids": [
        391
      ],
      "costs": [
        -3.0969804620096197
      ],
      "trial": 391,
      "walltime": 55.02043604850769
    }
  ],
  "state": {
    "queue": [
      [
        400,
        1
      ]
    ]
  }
}