{
  "seed": 4,
  "policy": [
    2,
    3,
    5,
    5
  ],
  "policy_name": "leaf_policy_2_3_5_5",
  "n_trials": 400,
  "trials_per_block": 100,
  "n_initial_design_configs": 25,
  "final_incumbent_cost": -3.3169600718194583,
  "milestone_best_costs": {
    "100": -3.160367557736867,
    "200": -3.312416068289278,
    "300": -3.313978107453354,
    "400": -3.3169600718194583
  },
  "incumbent": {
    "x1": 0.220069717448,
    "x2": 0.1398200021154,
    "x3": 0.4730149533593,
    "x4": 0.2743461762951,
    "x5": 0.3123280494984,
    "x6": 0.6564066462153
  },
  "run_dir": "/home/io632776/experiments/adaptive-smac/experiments/hartmann/06_brute_force_leaf_size/hartmann_6d_bruteforce_leaf_policies_400_trials_leaf_1_2_3_5/leaf_policy_2_3_5_5/4"
}