{
  "seed": 1,
  "policy": [
    3,
    2,
    5,
    2
  ],
  "policy_name": "leaf_policy_3_2_5_2",
  "n_trials": 400,
  "trials_per_block": 100,
  "n_initial_design_configs": 25,
  "final_incumbent_cost": -3.196494119795834,
  "milestone_best_costs": {
    "100": -2.1499662449898644,
    "200": -3.1034371702255052,
    "300": -3.18358244319628,
    "400": -3.196494119795834
  },
  "incumbent": {
    "x1": 0.4111107177656,
    "x2": 0.8794824126774,
    "x3": 0.7670058640712,
    "x4": 0.5694083378556,
    "x5": 0.1708052446808,
    "x6": 0.0313907057091
  },
  "run_dir": "/home/io632776/experiments/adaptive-smac/experiments/hartmann/06_brute_force_leaf_size/hartmann_6d_bruteforce_leaf_policies_400_trials_leaf_1_2_3_5/leaf_policy_3_2_5_2/1"
}